{
  "id": "f9bbd1ec-bde9-475f-9609-da70f566db2b",
  "name": "CUSTOMER_PERSONAL",
  "notes": "Personal details about the customer.",
  "dataConnection": {
    "id": "b9afa559-3a59-4404-ae0f-0c33ef9c7515",
    "name": "Source",
    "classifications": [
      {
        "id": "",
        "group": "Solution Layer",
        "classification": "Operational System",
        "notes": "\u0027Source\u0027 layer, representing the operational systems or interfaces that provide data to the solution."
      }
    ],
    "extensions": [
      {
        "key": "location",
        "value": "dbo"
      },
      {
        "key": "connectionString",
        "value": "Data Source=.;Initial Catalog=000_Source;Integrated Security=True;Trust Server Certificate=True"
      },
      {
        "key": "connectionType",
        "value": "MSSQLDB"
      },
      {
        "key": "datastore",
        "value": "000_Source"
      }
    ]
  },
  "dataItems": [
    {
      "id": "a2222222-2222-2222-2222-222222222222",
      "name": "CustomerID",
      "ordinalPosition": 1,
      "isPrimaryKey": true,
      "dataType": "int"
    },
    {
      "id": "1e12753f-d184-4f33-a391-c7f16af7f1cb",
      "name": "Given",
      "ordinalPosition": 2,
      "dataType": "varchar",
      "characterLength": 100
    },
    {
      "id": "dc57b758-e8c4-48b1-935f-a51c9dd46eb0",
      "name": "Surname",
      "ordinalPosition": 3,
      "dataType": "varchar",
      "characterLength": 100
    },
    {
      "id": "2b0e0a8c-14c4-44ab-9909-e3354c31d1e0",
      "name": "Suburb",
      "ordinalPosition": 4,
      "dataType": "varchar",
      "characterLength": 50
    },
    {
      "id": "38733dcf-8102-4691-8714-82a98db5e0c7",
      "name": "State",
      "ordinalPosition": 5,
      "dataType": "varchar",
      "characterLength": 3
    },
    {
      "id": "a39e1aa2-3eee-443d-a2dd-db403d297fed",
      "name": "Postcode",
      "ordinalPosition": 6,
      "dataType": "varchar",
      "characterLength": 6
    },
    {
      "id": "613bfdab-7ace-4d1f-bc96-1c87abe522bb",
      "name": "Country",
      "ordinalPosition": 7,
      "dataType": "varchar",
      "characterLength": 100
    },
    {
      "id": "ba076d4e-cc73-4c2e-92ee-a4242a97b8ba",
      "name": "Pronoun",
      "ordinalPosition": 8,
      "dataType": "varchar",
      "characterLength": 1
    },
    {
      "id": "840e5fe9-bc5a-480e-86f2-8a4326d50acb",
      "name": "DOB",
      "ordinalPosition": 9,
      "dataType": "date",
      "numericScale": 0
    },
    {
      "id": "b4978acb-2a34-479f-a3ec-05aa44692eee",
      "name": "Referee_Offer_Made",
      "ordinalPosition": 10,
      "dataType": "int"
    },
    {
      "id": "d727fca7-3e58-43c0-2222-222222222222",
      "name": "Valid_From",
      "ordinalPosition": 11,
      "dataType": "date",
      "numericScale": 0
    }
  ],
  "relationships": [
    {
      "id": "0563740d-7c9b-4d87-b26d-f2dc7834b09b",
      "name": "CUSTOMER_PERSONAL to CUSTOMER_OFFER",
      "type": "Foreign Key",
      "cardinality": "OneToMany",
      "relatedDataObjectId": "1ba0099f-23f6-4cbb-ae06-7d1cb7b4e713",
      "notes": "Created from graph edge",
      "dataItemMappings": [
        {
          "sourceDataItemIds": [
            "a2222222-2222-2222-2222-222222222222"
          ],
          "targetDataItemId": "a1111111-1111-1111-1111-111111111111"
        }
      ]
    },
    {
      "id": "b727c761-f307-4eee-ba55-4a1a840e59d6",
      "name": "CUSTOMER_PERSONAL to CUSTOMER_CONTACT",
      "type": "Foreign Key",
      "cardinality": "OneToMany",
      "relatedDataObjectId": "8e10e555-e103-4a42-8d5a-af0beb82f15d",
      "notes": "Created from graph edge",
      "dataItemMappings": [
        {
          "sourceDataItemIds": [
            "a2222222-2222-2222-2222-222222222222"
          ],
          "targetDataItemId": "a3333333-3333-3333-3333-333333333333"
        }
      ]
    },
    {
      "id": "9cadec9b-fa1f-41f5-9551-0d95636b077b",
      "name": "CUSTOMER_PERSONAL to CUST_MEMBERSHIP",
      "type": "Foreign Key",
      "cardinality": "OneToMany",
      "relatedDataObjectId": "db1bf76d-9e40-4e97-bf40-ed707862e8b9",
      "notes": "Created from graph edge",
      "dataItemMappings": [
        {
          "sourceDataItemIds": [
            "a2222222-2222-2222-2222-222222222222"
          ],
          "targetDataItemId": "a4444444-4444-4444-4444-444444444444"
        }
      ]
    },
    {
      "id": "5f93d647-2e2e-4576-ad0e-28e31524c79b",
      "name": "CUSTOMER_PERSONAL to PERSONALISED_COSTING",
      "type": "Foreign Key",
      "cardinality": "OneToMany",
      "relatedDataObjectId": "bee610e8-9121-48fc-a450-fac925f15db8",
      "notes": "Created from graph edge",
      "dataItemMappings": [
        {
          "sourceDataItemIds": [
            "a2222222-2222-2222-2222-222222222222"
          ],
          "targetDataItemId": "b35008a1-d0ef-4af2-b9da-c0503727c340"
        }
      ]
    }
  ],
  "classifications": [
    {
      "id": "3cb478a3-f7cb-436d-8cba-171988808add",
      "group": "Solution Layer",
      "classification": "Operational System",
      "notes": "\u0027Source\u0027 layer, representing the operational systems or interfaces that provide data to the solution."
    },
    {
      "id": "43b6ce73-62ba-43a5-a330-3bf9440599e4",
      "group": "Solution Area",
      "classification": "Operational System"
    }
  ],
  "extensions": [
    {
      "key": "originatingSystem",
      "value": "SAVEMORE",
      "notes": "SaveMore source system"
    }
  ],
  "templateMappings": [
    {
      "templateFileName": "/DataObjects/SourceSqlServerGenerateTable.handlebars"
    },
    {
      "templateFileName": "/DataObjects/LandingSqlServerGenerateTable.handlebars"
    },
    {
      "templateFileName": "/DataObjects/PersistentStagingSqlServerGenerateTable.handlebars"
    }
  ]
}